{
  "name": "speechy",
  "logo_letter": "s",
  "app_framework": "vue",
  "webpack_dev": {
    "entry": {
      "popup": "/js/entry/popup.js",
      "content": "/js/entry/content.js",
      "injected": "/js/entry/injected.js",
      "background": "/js/entry/background.js"
    },
    "resolve":{
    "extensions":[".js"]
    },
    "devtool": "source-map",
    "optimization": {
      "minimize": false
    }
  },
  "webpack_prod": {
    "entry": {
      "popup": "/js/entry/popup.js",
      "content": "/js/entry/content.js",
      "injected": "/js/entry/injected.js",
      "background": "/js/entry/background.js"
    },
    "resolve":{
    "extensions":[".js"]
    },
    "devtool": false,
    "optimization": {
      "minimize": false
    }
  }
}
